auth/__init__.py
auth/chrome_fix.py
auth/um_authenticator.py
downloader/__init__.py
downloader/pdf_downloader.py
scraper/__init__.py
scraper/paper_scraper.py
scripts/debug_status_dropdown.py
scripts/example_usage.py
scripts/main.py
umpaper_fetch/__init__.py
umpaper_fetch/cli.py
umpaper_fetch/auth/__init__.py
umpaper_fetch/auth/chrome_fix.py
umpaper_fetch/auth/um_authenticator.py
umpaper_fetch/downloader/__init__.py
umpaper_fetch/downloader/pdf_downloader.py
umpaper_fetch/scraper/__init__.py
umpaper_fetch/scraper/paper_scraper.py
umpaper_fetch/utils/__init__.py
umpaper_fetch/utils/logger.py
umpaper_fetch/utils/zip_creator.py
umpaper_fetch-1.0.7.dist-info/licenses/LICENSE
utils/__init__.py
utils/logger.py
utils/zip_creator.py
umpaper_fetch-1.0.7.dist-info/METADATA
umpaper_fetch-1.0.7.dist-info/WHEEL
umpaper_fetch-1.0.7.dist-info/entry_points.txt
umpaper_fetch-1.0.7.dist-info/top_level.txt
umpaper_fetch-1.0.7.dist-info/RECORD
