Metadata-Version: 2.4
Name: umpaper-fetch
Version: 1.0.7
Summary: Automated downloader for University Malaya past year exam papers
Home-page: https://github.com/MarcusMQF/umpaper-fetch
Author: Marcus Mah
Author-email: Marcus Mah <marcusmah6969@gmail.com>
License: MIT
Project-URL: Homepage, https://github.com/MarcusMQF/umpaper-fetch
Project-URL: Documentation, https://github.com/MarcusMQF/umpaper-fetch#readme
Project-URL: Repository, https://github.com/MarcusMQF/umpaper-fetch
Project-URL: Bug Reports, https://github.com/MarcusMQF/umpaper-fetch/issues
Keywords: university,malaya,um,exam,papers,downloader,automation,selenium
Classifier: Development Status :: 4 - Beta
Classifier: Intended Audience :: Education
Classifier: Topic :: Education
Classifier: Topic :: Internet :: WWW/HTTP :: Browsers
Classifier: Topic :: Utilities
Classifier: License :: OSI Approved :: MIT License
Classifier: Programming Language :: Python :: 3
Classifier: Programming Language :: Python :: 3.8
Classifier: Programming Language :: Python :: 3.9
Classifier: Programming Language :: Python :: 3.10
Classifier: Programming Language :: Python :: 3.11
Classifier: Programming Language :: Python :: 3.12
Classifier: Operating System :: OS Independent
Classifier: Environment :: Console
Requires-Python: >=3.8
License-File: LICENSE
Requires-Dist: selenium>=4.15.2
Requires-Dist: requests>=2.31.0
Requires-Dist: beautifulsoup4>=4.12.2
Requires-Dist: webdriver-manager>=4.0.1
Requires-Dist: lxml>=4.9.3
Requires-Dist: urllib3>=2.0.7
Requires-Dist: certifi>=2023.7.22
Requires-Dist: tqdm>=4.66.1
Provides-Extra: dev
Requires-Dist: pytest>=7.0; extra == "dev"
Requires-Dist: pytest-cov>=4.0; extra == "dev"
Requires-Dist: black>=22.0; extra == "dev"
Requires-Dist: flake8>=5.0; extra == "dev"
Requires-Dist: mypy>=1.0; extra == "dev"
Dynamic: author
Dynamic: home-page
Dynamic: license-file
Dynamic: requires-python
